{"cameraMode":{"drawMode":0,"name":"Shaded","section":"Shading Mode"},"sceneLighting":true,"audioPlay":false,"sceneViewState":{"m_AlwaysRefresh":false,"showFog":true,"showSkybox":true,"showFlares":true,"showImageEffects":true,"showParticleSystems":true,"showVisualEffectGraphs":true,"m_FxEnabled":true},"in2DMode":false,"pivot":{"x":0.0,"y":1.0,"z":5.0},"rotation":{"x":0.17164592444896699,"y":-0.0014779086923226715,"z":0.00025739744887687266,"w":0.9851586222648621},"size":11.765743255615235,"orthographic":false}